weather3reporter/cli.py
weather3reporter/utils.py
weather3reporter-2.0.1.dist-info/LICENSE
weather3reporter-2.0.1.dist-info/METADATA
weather3reporter-2.0.1.dist-info/WHEEL
weather3reporter-2.0.1.dist-info/entry_points.txt
weather3reporter-2.0.1.dist-info/top_level.txt
weather3reporter-2.0.1.dist-info/RECORD
