Metadata-Version: 2.1
Name: weather3reporter
Version: 2.0.1
Summary: A Python package to get weather reports for any location.
Home-page: https://github.com/nikhilkumarsingh/weather-reporter
Author: shehan
Author-email: shehan9909@gmail.com
License: MIT
Platform: UNKNOWN
Classifier: License :: OSI Approved :: MIT License
Classifier: Programming Language :: Python :: 3
Classifier: Programming Language :: Python :: 3.7
Requires-Dist: requests
